masai/__init__.py
masai/AgentManager/AgentManager.py
masai/AgentManager/__init__.py
masai/Agents/__init__.py
masai/Agents/base_agent.py
masai/Agents/singular_agent.py
masai/Config/__init__.py
masai/Config/config.py
masai/GenerativeModel/__init__.py
masai/GenerativeModel/generativeModels.py
masai/GenerativeModel/parameter_config.py
masai/GenerativeModel/baseGenerativeModel/basegenerativeModel.py
masai/GenerativeModel/vanilla_wrappers/__init__.py
masai/GenerativeModel/vanilla_wrappers/base_chat_model.py
masai/GenerativeModel/vanilla_wrappers/gemini_wrapper.py
masai/GenerativeModel/vanilla_wrappers/openai_wrapper.py
masai/Memory/InMemoryStore.py
masai/Memory/LongTermMemory.py
masai/MultiAgents/MultiAgent.py
masai/MultiAgents/TaskManager.py
masai/MultiAgents/__init__.py
masai/OMAN/__init__.py
masai/OMAN/oman.py
masai/Tools/Tool.py
masai/Tools/__init__.py
masai/Tools/PARSERs/json_parser.py
masai/Tools/logging_setup/logger.py
masai/Tools/utilities/cache.py
masai/Tools/utilities/deduplication_utils.py
masai/Tools/utilities/enhanced_streaming.py
masai/Tools/utilities/streaming_events.py
masai/Tools/utilities/tokenGenerationTool.py
masai/langgraph/__init__.py
masai/langgraph/core.py
masai/langgraph/state.py
masai/langgraph/graph/__init__.py
masai/langgraph/graph/state.py
masai/prompts/__init__.py
masai/prompts/chat_prompt_template.py
masai/prompts/prompt_templates.py
masai/prompts/Template/template.py
masai/pydanticModels/AnswerModel.py
masai/pydanticModels/omanModel.py
masai/pydanticModels/supervisorModels.py
masai/schema/__init__.py
masai/schema/document.py
masai_framework-0.5.2.dist-info/licenses/LICENSE
masai_framework-0.5.2.dist-info/METADATA
masai_framework-0.5.2.dist-info/WHEEL
masai_framework-0.5.2.dist-info/top_level.txt
masai_framework-0.5.2.dist-info/RECORD
