Metadata-Version: 2.4
Name: masai_framework
Version: 0.5.2
Summary: Multi-Agent System Framework for AI Agents with Vanilla SDK Wrappers and Custom LangGraph
Author-email: PILER <mrpolymathematica@gmail.com>
Requires-Python: >=3.9
License-File: LICENSE
Requires-Dist: openai>=2.6.0
Requires-Dist: google-genai>=1.46.0
Requires-Dist: pydantic>=2.12.0
Requires-Dist: python-dotenv>=1.0.0
Requires-Dist: requests>=2.32.0
Requires-Dist: tenacity>=9.1.0
Requires-Dist: tiktoken>=0.12.0
Requires-Dist: colorama>=0.4.6
Requires-Dist: json-repair>=0.39.1
Requires-Dist: aiofiles>=25.1.0
Requires-Dist: tqdm>=4.67.0
Requires-Dist: numpy==1.26.4
Requires-Dist: pandas>=2.3.3
Requires-Dist: redis>=6.4.0
Requires-Dist: networkx>=3.4.2
Requires-Dist: qdrant-client>=1.7.0
Provides-Extra: tools
Dynamic: license-file
